VERIFICATION/multiplier/multiplier.sv
module multiplier(input a,b,load,rst,clk,output product,op_ready);
  logic [3:0]a,b; 
  logic load,rst,clk;
  logic op_ready; //indicate whether multiplication is completed and ready for displaying result
  logic [7:0]product;
  
  reg [7:0]temp,temp_b,p;//temporary variables to store product of each bits
  assign temp={4'b0000,b}; //extending b to 8 bits
  always@(posedge clk)
    begin
      //when reset is high output is not ready for displaying result and p is made zero
      if(rst==1'b1)
        begin
         op_ready=1'b0;
         p=8'b0000_0000; 
	 product=8'b0000_0000; 
        end
      //when reset is low and load is high, A and B values are loaded and multiplication is performed and product is stored in the variable p.
      if(rst==1'b0 && load==1'b1)
        begin
          p=8'b0000_0000; //initially p is 0
          for(int i=0;i<4;i++) //iterating through all 4 bits of A
          begin
            if(a[i]==1) // if a bit of A is 1 then, temp is left shifted i times and stored in temp_b
            begin
              temp_b=temp<<i;
              p=p+temp_b; //successive addition is performed after each shift
              if(i==3) 
                op_ready=1'b1;//making op_ready flag 1 as we have final product which can be displayed.
            end
          end
        end
      //if(op_ready==1'b1)
        product=p; //p is assigned to product and product is observed in GUI
    end 
endmodule

HLDD/multiplier/multiplier_tb.sv
module multiplier_tb();
  logic [3:0]a,b;
  logic load,rst,clk;
  logic op_ready;
  logic [7:0]product,temp,temp_b,p;
  multiplier dut(.*);
  initial clk=1'b0;
  always #5 clk=~clk; //clock is pulsating for every 5ns

    initial begin
      rst=1'b0;a=4'b1000; b=4'b0011; #10; //A=8,B=3 input combination with no load signal
      load=1; #10; //load signal is enabled	
      rst=1'b1; #10;//reset is enabled, product will get reset
      
      rst=1'b0; a=4'b0010; b=4'b1011; #10; //A=10,B=11 input combination with no load signal
      load=1; #10;	
      rst=1'b1; #10;
      
       rst=1'b0; a=4'b1111; b=4'b1111; #10;//A=15,B=15 input combination with no load signal
      load=1; #10;	
      rst=1'b1; #10;
 end
  initial begin
   
    $dumpfile("test.vcd");
    $dumpvars;
     #180 $finish;
  end
endmodule

VERIFICATION/multiplier/test.vcd
$date
    Nov 28, 2022  14:49:30
$end
$version
    TOOL:	ncsim(64)	15.20-s086
$end
$timescale
    1 ns
$end

$scope module multiplier_tb $end
$var reg       4 !    a [3:0] $end
$var reg       4 "    b [3:0] $end
$var reg       1 #    load  $end
$var reg       1 $    rst  $end
$var reg       1 %    clk  $end
$var reg       1 &    op_ready  $end
$var reg       8 '    product [7:0] $end
$var reg       8 (    temp [7:0] $end
$var reg       8 )    temp_b [7:0] $end
$var reg       8 *    p [7:0] $end

$scope module dut $end
$var wire      4 +    a [3:0] $end
$var wire      4 ,    b [3:0] $end
$var wire      1 -    load  $end
$var wire      1 .    rst  $end
$var wire      1 /    clk  $end
$var reg       8 0    product [7:0] $end
$var reg       1 1    op_ready  $end
$var reg       8 2    temp [7:0] $end
$var reg       8 3    temp_b [7:0] $end
$var reg       8 4    p [7:0] $end
$upscope $end

$upscope $end

$enddefinitions $end
$dumpvars
b1000 !
b11 "
x#
0$
0%
x&
bx '
bx (
bx )
bx *
b1000 +
b11 ,
x-
0.
0/
bx 0
x1
b11 2
bx 3
bx 4
$end
#5
1%
1/
#10
1#
0%
0/
1-
#15
1%
1/
b0 4
b11000 3
b11000 4
11
b11000 0
b11000 '
1&
#20
1$
0%
0/
1.
#25
1%
1/
01
b0 4
b0 0
b0 '
0&
#30
0$
b10 !
b1011 "
0%
0/
b1011 ,
b10 +
0.
b1011 2
#35
1%
1/
b10110 3
b10110 4
b10110 0
b10110 '
#40
0%
0/
#45
1%
1/
b0 4
b10110 4
#50
1$
0%
0/
1.
#55
1%
1/
b0 4
b0 0
b0 '
#60
0$
b1111 !
b1111 "
0%
0/
b1111 ,
b1111 +
0.
b1111 2
#65
1%
1/
b1111 3
b1111 4
b11110 3
b101101 4
b111100 3
b1101001 4
b1111000 3
b11100001 4
11
b11100001 0
b11100001 '
1&
#70
0%
0/
#75
1%
1/
b0 4
b1111 3
b1111 4
b11110 3
b101101 4
b111100 3
b1101001 4
b1111000 3
b11100001 4
#80
1$
0%
0/
1.
#85
1%
1/
01
b0 4
b0 0
b0 '
0&
