Gates/or/or.sv
module or_gate(input a,b, output reg y);
	always @(a,b)
	begin
		if(a==1'b0 && b==1'b0)
			y =1'b0;
		else
			y =1'b1;
	end
endmodule

Gates/and/and.sv
module and_gate(input a,b, output reg y);
	always @(a,b)
	begin
		if(a==1'b1 && b==1'b1)
			#1 y =1'b1;
		else
			#1 y =1'b0;
	end
endmodule

Gates/xor/xor.sv
module xor_gate(input a,b, output reg y);
	always @(a,b)
	begin
		if(a!=b)
			y =1'b1;
		else
			y =1'b0;
	end
endmodule

HLDD/Adder/FA/FA.sv
`include "../and/and.sv"
`include "../or/or.sv"
`include "../xor/xor.sv"

module FA(input a,b,c,output reg sum,cout);
	wire ab,abc,a_b;
	xor_gate sum1(a,b,a_b);
	xor_gate sum2(a_b,c,sum);
	and_gate car1(a_b,c,abc);
	and_gate car2(a,b,ab);
	or_gate car3(abc,ab,cout);
endmodule

HLDD/Adder/FA/FA_tb.sv
module FA_tb();
 reg a,b,c;
 wire sum,cout;
 FA dut(.*);
 initial begin
  a=1'b0;b=1'b0;c=1'b0;#5;
  a=1'b0;b=1'b0;c=1'b1;#5;
  a=1'b0;b=1'b1;c=1'b0;#5;
  a=1'b0;b=1'b1;c=1'b1;#5;
  a=1'b1;b=1'b0;c=1'b0;#5;
  a=1'b1;b=1'b0;c=1'b1;#5;
  a=1'b1;b=1'b1;c=1'b0;#5;
  a=1'b1;b=1'b1;c=1'b1;#5;
 end
 initial begin
 $dumpfile("test.vcd");
 $dumpvars();
 end
endmodule

HLDD/Adder/FA/test.vcd
$date
    Nov  8, 2022  17:27:15
$end
$version
    TOOL:	ncsim(64)	15.20-s086
$end
$timescale
    1 ns
$end

$scope module FA_tb $end
$var reg       1 !    a  $end
$var reg       1 "    b  $end
$var reg       1 #    c  $end
$var wire      1 $    sum  $end
$var wire      1 %    cout  $end

$scope module dut $end
$var wire      1 &    a  $end
$var wire      1 '    b  $end
$var wire      1 (    c  $end
$var reg       1 )    sum  $end
$var reg       1 *    cout  $end
$var wire      1 +    ab  $end
$var wire      1 ,    abc  $end
$var wire      1 -    a_b  $end

$scope module sum1 $end
$var wire      1 &    a  $end
$var wire      1 '    b  $end
$var reg       1 .    y  $end
$upscope $end


$scope module sum2 $end
$var wire      1 -    a  $end
$var wire      1 (    b  $end
$var reg       1 /    y  $end
$upscope $end


$scope module car1 $end
$var wire      1 -    a  $end
$var wire      1 (    b  $end
$var reg       1 0    y  $end
$upscope $end


$scope module car2 $end
$var wire      1 &    a  $end
$var wire      1 '    b  $end
$var reg       1 1    y  $end
$upscope $end


$scope module car3 $end
$var wire      1 ,    a  $end
$var wire      1 +    b  $end
$var reg       1 2    y  $end
$upscope $end

$upscope $end

$upscope $end

$enddefinitions $end
$dumpvars
0!
0"
0#
0$
x%
0&
0'
0(
0)
x*
x+
x,
0-
0.
0/
x0
x1
x2
$end
#1
00
01
0+
0,
02
0*
0%
#5
1#
1(
1/
1)
1$
#10
1"
0#
0(
1'
0/
1.
1-
1/
0)
0$
1)
1$
#15
1#
1(
0/
0)
0$
#16
10
1,
12
1*
1%
#20
1!
0"
0#
0(
0'
1&
1/
1)
1$
#21
00
0,
02
0*
0%
#25
1#
1(
0/
0)
0$
#26
10
1,
12
1*
1%
#30
1"
0#
0(
1'
1/
0.
0-
0/
1)
1$
0)
0$
#31
00
11
1+
0,
#35
1#
1(
1/
1)
1$
