VER/counter/Acounter.sv
module Acounter(clk,j,k,q1,q2,q3,q1b,q2b,q3b);
 input j,k,clk;
 output q1,q2,q3,q1b,q2b,q3b;
 reg q1,q2,q3;
 //wire q1;
 //initial begin a=1'b1;b=
 jk jk1(clk,j,k,q1,q1b);
 jk jk2(q1,j,k,q2,q2b);
 jk jk3(q2,j,k,q3,q3b);
endmodule

module jk(clk,j,k,q,qb);
  input clk,j,k;
  output q,qb;
  reg q,qb;
  //initial begin q=0;qb=1; end
  always @(negedge clk)
      case({j,k})
        {1'b0,1'b0}: begin q=q;qb=qb; end
        {1'b0,1'b1}: begin q=0;qb=~q; end
        {1'b1,1'b0}: begin q=1;qb=~q; end
        {1'b1,1'b1}: begin q=~q;qb=~q; end
      endcase
endmodule

HLDD/counter/test_Acounter.sv
module jk_tb();
  reg clk,j,k;
  wire q1,q2,q3,q1b,q2b,q3b;
  Acounter dut(.*);
  initial clk =1'b0;
  always #5 clk=~clk;
  initial begin 
      j=1'b1;k=1'b0;
   #7  j=1'b0;k=1'b1;
   
   #4  j=1'b1;k=1'b1;
  
  end
  initial begin
    $dumpfile("dump.vcd");
    $dumpvars;
    #80 $finish;
  end
endmodule

VER/counter/dump.vcd
$date
    Oct 18, 2022  15:31:14
$end
$version
    TOOL:	ncsim(64)	15.20-s086
$end
$timescale
    1 ns
$end

$scope module jk_tb $end
$var reg       1 !    clk  $end
$var reg       1 "    j  $end
$var reg       1 #    k  $end
$var wire      1 $    q1  $end
$var wire      1 %    q2  $end
$var wire      1 &    q3  $end
$var wire      1 '    q1b  $end
$var wire      1 (    q2b  $end
$var wire      1 )    q3b  $end

$scope module dut $end
$var wire      1 *    j  $end
$var wire      1 +    k  $end
$var wire      1 ,    clk  $end
$var reg       1 -    q1  $end
$var reg       1 .    q2  $end
$var reg       1 /    q3  $end
$var wire      1 '    q1b  $end
$var wire      1 (    q2b  $end
$var wire      1 )    q3b  $end

$scope module jk1 $end
$var wire      1 ,    clk  $end
$var wire      1 *    j  $end
$var wire      1 +    k  $end
$var reg       1 0    q  $end
$var reg       1 1    qb  $end
$upscope $end


$scope module jk2 $end
$var wire      1 2    clk  $end
$var wire      1 *    j  $end
$var wire      1 +    k  $end
$var reg       1 3    q  $end
$var reg       1 4    qb  $end
$upscope $end


$scope module jk3 $end
$var wire      1 5    clk  $end
$var wire      1 *    j  $end
$var wire      1 +    k  $end
$var reg       1 6    q  $end
$var reg       1 7    qb  $end
$upscope $end

$upscope $end

$upscope $end

$enddefinitions $end
$dumpvars
0!
1"
0#
1$
x%
x&
0'
x(
x)
1*
0+
0,
1-
x.
x/
10
01
12
x3
x4
x5
x6
x7
$end
#5
1!
1,
#7
0"
1#
1+
0*
#10
0!
0,
00
11
1'
0-
02
0$
03
14
1(
0.
05
0%
06
17
1)
0/
0&
#11
1"
1*
#15
1!
1,
#20
0!
0,
10
01
0'
1-
12
1$
#25
1!
1,
#30
0!
0,
00
11
1'
0-
02
0$
13
04
0(
1.
15
1%
#35
1!
1,
#40
0!
0,
10
01
0'
1-
12
1$
#45
1!
1,
#50
0!
0,
00
11
1'
0-
02
0$
03
14
1(
0.
05
0%
16
07
0)
1/
1&
#55
1!
1,
#60
0!
0,
10
01
0'
1-
12
1$
#65
1!
1,
#70
0!
0,
00
11
1'
0-
02
0$
13
04
0(
1.
15
1%
