VERIFICATION/seq_mul/SEQ_MUL/controlpath.sv
module controlpath(input clk,zero,start,output loadA,loadB,decB);
	logic clk,zero,start,loadA,loadB,decB;
  typedef enum {s0,s1,s2,s3,s4} State;
	State state;
	always @(posedge clk)
	begin
		case(state)
			s0:  if(start) state=s1;
			s1:  state=s2;
			s2:  state=s3;
			s3:  if(zero) state=s4;
			s4:  state=s0;
			default: state=s0;
		endcase
	end
  always @(state)
	begin
		case(state)
				s0:  begin loadA=0; loadB=0; decB=0; end
				s1:  begin loadA=1;end
				s2:  begin loadA=0;loadB=1;decB=0; end
				s3:  begin loadA=0;loadB=0;decB=1; end
				s4:  begin loadA=0; loadB=0; decB=0; end
				default: state=s0;
		endcase
    end
endmodule

VERIFICATION/seq_mul/SEQ_MUL/datapath.sv
module data_path(input clk,A,B,loadA,loadB,decB,loadF,clear,output zero,product);
	logic [1:0]A;
	logic [1:0]B;
	logic [3:0]product;
	logic loadA,loadB,decB,loadF,clear,zero;
	logic [1:0]P;
	logic [1:0]Q;
	regA r1(A,loadA,clk,P);
	regB r2(B,loadB,decB,clk,Q);
	regF r3(P,loadF,decB,clk,product);
	comparator r4(Q,clk,zero);
	
endmodule
	
module regA(input A,loadA,clk,output P);
	logic [1:0]A;
	logic [1:0]P;
	logic clk,loadA;	
	always@(posedge clk)
	begin
		if(loadA)
			 P=A;
	end
endmodule


module regB(input B,loadB,decB,clk,output Q);
	logic [1:0]B;
	logic [1:0]Q;
	logic clk,loadB,decB;
	always@(posedge clk)
	begin
		if(loadB==1'b1 && decB == 1'b0)
			 Q=B-1;
		else if(loadB==1'b0 && decB == 1'b1)
		begin
          if(Q==0)
            Q=B;
          else
              Q=Q-1;
        end
	end
endmodule

module regF(input P,loadF,decB,clk,output product);
	logic [1:0]P,Q;
	logic [3:0]product;
	logic loadF,clear,clk;
	
	always @(posedge clk)
	begin
		if(!decB)
			product=0;
		else
			//if(Q==0)
			//	product=0;
			//else
			product=product+P;
	end
endmodule

module comparator(input B,clk,output zero);
	logic [1:0]B;
	logic zero;
	always @( B)
	if(B==1'b0)
		zero=1;
	else
		zero=0;
endmodule

VERIFICATION/seq_mul/SEQ_MUL/testbench.sv
module regA_tb();
	logic [1:0]A;
	logic [1:0]P;
	logic clk,loadA;
	logic [1:0]B;
	logic [1:0]Q;
	logic loadB,decB,start;
	logic [1:0]product;
	logic loadF,clear;
	logic zero;/*
	logic [1:0]B;
	clk;
	*/
	
	//regA DUT(.*);
	//regB dut(.*);
	//regF dut(.*);
	//comparator dut1(.*);
	data_path dut(.*);
 	controlpath dut1(.*);
	initial clk=1'b0;
	always #5 clk=~clk;
	initial begin
		A=2;B=2;
      start=1;
      /*clear=1'b1;#10;
		loadA=0; loadB=0; #10;
		loadA=1;loadB=1;decB=0; #30;
		//#30;
		loadB=0;decB=1;clear=1'b0; #30;
		B=3;#20;*/
		
		
	end /*
	//initial begin
		B=3;#10;
		loadB=0; #10;
		loadB=1;decB=0; #10;
		loadB=0;decB=1; #10;
	end
	initial begin
		B=0; 	clear=1'b1; #20;//clear=1'b1;
		B=3; 	clear=1'b1; #20;
		clear=1'b0; 
	end*/
	initial begin
		$dumpfile("test.vcd");
		$dumpvars;
		#200 $finish;
	end
endmodule

VERIFICATION/seq_mul/test.vcd
$date
    Dec 26, 2022  21:13:27
$end
$version
    TOOL:	ncsim(64)	15.20-s086
$end
$timescale
    1 ns
$end

$scope module regA_tb $end
$var reg       2 !    A [1:0] $end
$var reg       2 "    P [1:0] $end
$var reg       1 #    clk  $end
$var reg       1 $    loadA  $end
$var reg       2 %    B [1:0] $end
$var reg       2 &    Q [1:0] $end
$var reg       1 '    loadB  $end
$var reg       1 (    decB  $end
$var reg       1 )    start  $end
$var reg       2 *    product [1:0] $end
$var reg       1 +    loadF  $end
$var reg       1 ,    clear  $end
$var reg       1 -    zero  $end

$scope module dut $end
$var wire      1 .    clk  $end
$var wire      2 /    A [1:0] $end
$var wire      2 0    B [1:0] $end
$var wire      1 1    loadA  $end
$var wire      1 2    loadB  $end
$var wire      1 3    decB  $end
$var wire      1 4    loadF  $end
$var wire      1 5    clear  $end
$var reg       1 6    zero  $end
$var reg       4 7    product [3:0] $end
$var reg       2 8    P [1:0] $end
$var reg       2 9    Q [1:0] $end

$scope module r1 $end
$var wire      2 /    A [1:0] $end
$var wire      1 1    loadA  $end
$var wire      1 .    clk  $end
$var reg       2 :    P [1:0] $end
$upscope $end


$scope module r2 $end
$var wire      2 0    B [1:0] $end
$var wire      1 2    loadB  $end
$var wire      1 3    decB  $end
$var wire      1 .    clk  $end
$var reg       2 ;    Q [1:0] $end
$upscope $end


$scope module r3 $end
$var wire      2 <    P [1:0] $end
$var wire      1 4    loadF  $end
$var wire      1 3    decB  $end
$var wire      1 .    clk  $end
$var reg       4 =    product [3:0] $end
$var reg       2 >    Q [1:0] $end
$var reg       1 ?    clear  $end
$upscope $end


$scope module r4 $end
$var wire      2 @    B [1:0] $end
$var wire      1 .    clk  $end
$var reg       1 A    zero  $end
$upscope $end

$upscope $end


$scope module dut1 $end
$var wire      1 B    clk  $end
$var wire      1 C    zero  $end
$var wire      1 D    start  $end
$var reg       1 E    loadA  $end
$var reg       1 F    loadB  $end
$var reg       1 G    decB  $end
$var reg      32 H    state [31:0] $end
$upscope $end

$upscope $end

$enddefinitions $end
$dumpvars
b10 !
bx "
0#
x$
b10 %
bx &
x'
x(
1)
bx *
x+
x,
x-
0.
b10 /
b10 0
x1
x2
x3
x4
x5
x6
bx 7
bx 8
bx 9
bx :
bx ;
bx <
bx =
bx >
x?
bx @
xA
0B
xC
1D
xE
xF
xG
b0 H
$end
#5
1#
1B
1.
b1 H
1E
1$
11
#10
0#
0B
0.
#15
1#
1B
1.
b10 H
b10 :
0E
1F
0G
0(
1'
0$
b10 8
b10 <
01
12
03
#20
0#
0B
0.
#25
1#
1B
1.
b11 H
b0 =
b1 ;
0F
1G
1(
0'
b1 9
b0 7
b1 @
02
13
0A
b0 *
06
0-
0C
#30
0#
0B
0.
#35
1#
1B
1.
b10 =
b0 ;
b0 9
b10 7
b0 @
1A
b10 *
16
1-
1C
#40
0#
0B
0.
#45
1#
1B
1.
b100 H
b100 =
b10 ;
0G
0(
b10 9
b100 7
b10 @
03
0A
b0 *
06
0-
0C
#50
0#
0B
0.
#55
1#
1B
1.
b0 H
b0 =
b0 7
#60
0#
0B
0.
#65
1#
1B
1.
b1 H
1E
1$
11
#70
0#
0B
0.
#75
1#
1B
1.
b10 H
0E
1F
1'
0$
01
12
#80
0#
0B
0.
#85
1#
1B
1.
b11 H
b1 ;
0F
1G
1(
0'
b1 9
b1 @
02
13
#90
0#
0B
0.
#95
1#
1B
1.
b10 =
b0 ;
b0 9
b10 7
b0 @
1A
b10 *
16
1-
1C
#100
0#
0B
0.
#105
1#
1B
1.
b100 H
b100 =
b10 ;
0G
0(
b10 9
b100 7
b10 @
03
0A
b0 *
06
0-
0C
#110
0#
0B
0.
#115
1#
1B
1.
b0 H
b0 =
b0 7
#120
0#
0B
0.
#125
1#
1B
1.
b1 H
1E
1$
11
#130
0#
0B
0.
#135
1#
1B
1.
b10 H
0E
1F
1'
0$
01
12
#140
0#
0B
0.
#145
1#
1B
1.
b11 H
b1 ;
0F
1G
1(
0'
b1 9
b1 @
02
13
#150
0#
0B
0.
#155
1#
1B
1.
b10 =
b0 ;
b0 9
b10 7
b0 @
1A
b10 *
16
1-
1C
#160
0#
0B
0.
#165
1#
1B
1.
b100 H
b100 =
b10 ;
0G
0(
b10 9
b100 7
b10 @
03
0A
b0 *
06
0-
0C
#170
0#
0B
0.
#175
1#
1B
1.
b0 H
b0 =
b0 7
#180
0#
0B
0.
#185
1#
1B
1.
b1 H
1E
1$
11
#190
0#
0B
0.
#195
1#
1B
1.
b10 H
0E
1F
1'
0$
01
12
